amarthyas_demo_package/Binomialdistribution.py
amarthyas_demo_package/Gaussiandistribution.py
amarthyas_demo_package/Generaldistribution.py
amarthyas_demo_package/__init__.py
amarthyas_demo_package-0.0.dist-info/METADATA
amarthyas_demo_package-0.0.dist-info/WHEEL
amarthyas_demo_package-0.0.dist-info/top_level.txt
amarthyas_demo_package-0.0.dist-info/RECORD
