Metadata-Version: 2.1
Name: amarthyas_demo_package
Version: 0.0
Summary: Gaussian and Binomial distributions
Author-email: amarthya10@gmail.com
